{
  "type": "صحيح",
  "form": 8,
  "باب": "افْتِعَال",
  "title": "افْتَعَلَ يَفْتَعِلُ",
  "root_letters": [["ح", "ر", "م"]],
  "archetype": {
    "ماضي": {
      "معروف": "افْتَعَلَ",
      "مجهول": "افْتُعِلَ"
    },
    "مضارع": {
      "معروف": "يَفْتَعِلُ",
      "مجهول": "يُفْتَعِلُ"
    },
    "مصضر": ["افْتِعَالًا"],
    "فاعل": "مُفْتَعِلٌ",
    "مفعول": "مُفْتَعَلٌ",
    "أمر": "افْتَعِلْ",
    "نهي": "تَفْتَعِلْ"
  },
  "conjugations": {
    "ماضي": {
      "معروف": {
        "3rd": {
          "masculine": {
            "هُوَ": "افْتَعَلَ",
            "هُمَا": "افْتَعَلَا",
            "هُمْ": "افْتَعَلُوْا"
          },
          "feminine": {
            "هِيَ": "افْتَعَلَتْ",
            "هُمَا": "افْتَعَلَتَا",
            "هُنَّ": "افْتَعَلْنَ"
          }
        },
        "2nd": {
          "masculine": {
            "أَنْتَ": "افْتَعَلْتَ",
            "أَنْتُمَا": "افْتَعَلْتُمَا",
            "أَنْتُمْ": "افْتَعَلْتُمْ"
          },
          "feminine": {
            "أَنْتِ": "افْتَعَلْتِ",
            "أَنْتُمَا": "افْتَعَلْتُمَا",
            "أَنْتُنَّ": "افْتَعَلْتُنَّ"
          }
        },
        "1st": {
          "أَنَا": "افْتَعَلْتُ",
          "نَحْنُ": "افْتَعَلْنَا"
        }
      },
      "مجهول": {
        "3rd": {
          "masculine": {
            "هُوَ": "افْتُعِلَ",
            "هُمَا": "افْتُعِلَا",
            "هُمْ": "افْتُعِلُوْا"
          },
          "feminine": {
            "هِيَ": "افْتُعِلَتْ",
            "هُمَا": "افْتُعِلَتَا",
            "هُنَّ": "افْتُعِلْنَ"
          }
        },
        "2nd": {
          "masculine": {
            "أَنْتَ": "افْتُعِلْتَ",
            "أَنْتُمَا": "افْتُعِلْتُمَا",
            "أَنْتُمْ": "افْتُعِلْتُمْ"
          },
          "feminine": {
            "أَنْتِ": "افْتُعِلْتِ",
            "أَنْتُمَا": "افْتُعِلْتُمَا",
            "أَنْتُنَّ": "افْتُعِلْتُنَّ"
          }
        },
        "1st": {
          "أَنَا": "افْتُعِلْتُ",
          "نَحْنُ": "افْتُعِلْنَا"
        }
      }
    },
    "مضارع": {
      "معروف": {
        "3rd": {
          "masculine": {
            "هُوَ": "يَفْتَعِلُ",
            "هُمَا": "يَفْتَعِلَانِ",
            "هُمْ": "يَفْتَعِلُوْنَ"
          },
          "feminine": {
            "هِيَ": "تَفْتَعِلُ",
            "هُمَا": "تَفْتَعِلَانِ",
            "هُنَّ": "يَفْتَعِلْنَ"
          }
        },
        "2nd": {
          "masculine": {
            "أَنْتَ": "تَفْتَعِلُ",
            "أَنْتُمَا": "تَفْتَعِلَانِ",
            "أَنْتُمْ": "تَفْتَعِلُوْنَ"
          },
          "feminine": {
            "أَنْتِ": "تَفْتَعِلِيْنَ",
            "أَنْتُمَا": "تَفْتَعِلَانِ",
            "أَنْتُنَّ": "تَفْتَعِلْنَ"
          }
        },
        "1st": {
          "أَنَا": "أَفْتَعِلُ",
          "نَحْنُ": "نَفْتَعِلُ"
        }
      },
      "مجهول": {
        "3rd": {
          "masculine": {
            "هُوَ": "يُفْتَعَلُ",
            "هُمَا": "يُفْتَعَلَانِ",
            "هُمْ": "يُفْتَعَلُوْنَ"
          },
          "feminine": {
            "هِيَ": "تُفْتَعَلُ",
            "هُمَا": "تُفْتَعَلَانِ",
            "هُنَّ": "يُفْتَعَلْنَ"
          }
        },
        "2nd": {
          "masculine": {
            "أَنْتَ": "تُفْتَعَلُ",
            "أَنْتُمَا": "تُفْتَعَلَانِ",
            "أَنْتُمْ": "تُفْتَعَلُوْنَ"
          },
          "feminine": {
            "أَنْتِ": "تُفْتَعَلِيْنَ",
            "أَنْتُمَا": "تُفْتَعَلَانِ",
            "أَنْتُنَّ": "تُفْتَعَلْنَ"
          }
        },
        "1st": {
          "أَنَا": "أُفْتَعَلُ",
          "نَحْنُ": "نُفْتَعَلُ"
        }
      }
    },
    "نصب": {
      "معروف": {
        "3rd": {
          "masculine": {
            "هُوَ": "يَفْتَعِلَ",
            "هُمَا": "يَفْتَعِلَا",
            "هُمْ": "يَفْتَعِلُوْا"
          },
          "feminine": {
            "هِيَ": "تَفْتَعِلَ",
            "هُمَا": "تَفْتَعِلَا",
            "هُنَّ": "يَفْتَعِلْنَ"
          }
        },
        "2nd": {
          "masculine": {
            "أَنْتَ": "تَفْتَعِلَ",
            "أَنْتُمَا": "تَفْتَعِلَا",
            "أَنْتُمْ": "تَفْتَعِلُوْا"
          },
          "feminine": {
            "أَنْتِ": "تَفْتَعِلِيْ",
            "أَنْتُمَا": "تَفْتَعِلَا",
            "أَنْتُنَّ": "تَفْتَعِلْنَ"
          }
        },
        "1st": {
          "أَنَا": "أَفْتَعِلَ",
          "نَحْنُ": "نَفْتَعِلَ"
        }
      },
      "مجهول": {
        "3rd": {
          "masculine": {
            "هُوَ": "يُفْتَعَلَ",
            "هُمَا": "يُفْتَعَلَا",
            "هُمْ": "يُفْتَعَلُوْا"
          },
          "feminine": {
            "هِيَ": "تُفْتَعَلَ",
            "هُمَا": "تُفْتَعَلَا",
            "هُنَّ": "يُفْتَعَلْنَ"
          }
        },
        "2nd": {
          "masculine": {
            "أَنْتَ": "تُفْتَعَلَ",
            "أَنْتُمَا": "تُفْتَعَلَا",
            "أَنْتُمْ": "تُفْتَعَلُوْا"
          },
          "feminine": {
            "أَنْتِ": "تُفْتَعَلِيْ",
            "أَنْتُمَا": "تُفْتَعَلَا",
            "أَنْتُنَّ": "تُفْتَعَلْنَ"
          }
        },
        "1st": {
          "أَنَا": "أُفْتَعَلَ",
          "نَحْنُ": "نُفْتَعَلَ"
        }
      }
    },
    "جزم": {
      "معروف": {
        "3rd": {
          "masculine": {
            "هُوَ": "يَفْتَعِلْ",
            "هُمَا": "يَفْتَعِلَا",
            "هُمْ": "يَفْتَعِلُوْا"
          },
          "feminine": {
            "هِيَ": "تَفْتَعِلْ",
            "هُمَا": "تَفْتَعِلَا",
            "هُنَّ": "يَفْتَعِلْنَ"
          }
        },
        "2nd": {
          "masculine": {
            "أَنْتَ": "تَفْتَعِلْ",
            "أَنْتُمَا": "تَفْتَعِلَا",
            "أَنْتُمْ": "تَفْتَعِلُوْا"
          },
          "feminine": {
            "أَنْتِ": "تَفْتَعِلِيْ",
            "أَنْتُمَا": "تَفْتَعِلَا",
            "أَنْتُنَّ": "تَفْتَعِلْنَ"
          }
        },
        "1st": {
          "أَنَا": "أَفْتَعِلْ",
          "نَحْنُ": "نَفْتَعِلْ"
        }
      },
      "مجهول": {
        "3rd": {
          "masculine": {
            "هُوَ": "يُفْتَعَلْ",
            "هُمَا": "يُفْتَعَلَا",
            "هُمْ": "يُفْتَعَلُوْا"
          },
          "feminine": {
            "هِيَ": "تُفْتَعَلْ",
            "هُمَا": "تُفْتَعَلَا",
            "هُنَّ": "يُفْتَعَلْنَ"
          }
        },
        "2nd": {
          "masculine": {
            "أَنْتَ": "تُفْتَعَلْ",
            "أَنْتُمَا": "تُفْتَعَلَا",
            "أَنْتُمْ": "تُفْتَعَلُوْا"
          },
          "feminine": {
            "أَنْتِ": "تُفْتَعَلِيْ",
            "أَنْتُمَا": "تُفْتَعَلَا",
            "أَنْتُنَّ": "تُفْتَعَلْنَ"
          }
        },
        "1st": {
          "أَنَا": "أُفْتَعَلْ",
          "نَحْنُ": "نُفْتَعَلْ"
        }
      }
    },
    "أمر": {
      "2nd": {
        "masculine": {
          "أَنْتَ": "افْتَعِلْ",
          "أَنْتُمَا": "افْتَعِلَا",
          "أَنْتُمْ": "افْتَعِلُوْا"
        },
        "feminine": {
          "أَنْتِ": "افْتَعِلِيْ",
          "أَنْتُمَا": "افْتَعِلَا",
          "أَنْتُنَّ": "افْتَعِلْنَ"
        }
      }
    }
  }
}
