{
  "باب": "إِفْعَال",
  "form": 4,
  "archetype": {
    "root_letters": ["ح", "ب", "ب"],
    "ماضي": {
      "معروف": "أَفَعَّ",
      "مجهول": "أُفِعَّ"
    },
    "مضارع": {
      "معروف": "يُفِعُّ",
      "مجهول": "يُفَعُّ"
    },
    "مصضر": ["افْعَالًا"],
    "فاعل": "مُفِعٌّ",
    "مفعول": "مُفَعٌّ",
    "أمر": "أَفِعَّ",
    "نهي": "تُفِعْ"
  },
  "conjugations": {
    "ماضي": {
      "معروف": {
        "3rd": {
          "masculine": {
            "هُوَ": "أَفَعَّ",
            "هُمَا": "أَفَعَّا",
            "هُمْ": "أَفَعُّوْا"
          },
          "feminine": {
            "هِيَ": "أَفَعَّتْ",
            "هُمَا": "أَفَعَّتَا",
            "هُنَّ": "أَفْعَلْنَ"
          }
        },
        "2nd": {
          "masculine": {
            "أَنْتَ": "أَفْعَلْتَ",
            "أَنْتُمَا": "أَفْعَلْتُمَا",
            "أَنْتُمْ": "أَفْعَلتُمْ"
          },
          "feminine": {
            "أَنْتِ": "أَفْعَلْتِ",
            "أَنْتُمَا": "أَفْعَلْتُمَا",
            "أَنْتُنَّ": "أَفْعَلتُنَّ"
          }
        },
        "1st": {
          "أَنَا": "أَفْعَلْتُ",
          "نَحْنُ": "أَفْعَلْنَا"
        }
      },
      "مجهول": {
        "3rd": {
          "masculine": {
            "هُوَ": "أُفِعَّ",
            "هُمَا": "أُفِعَّا",
            "هُمْ": "أُفِعُّوْا"
          },
          "feminine": {
            "هِيَ": "أُفِعَّتْ",
            "هُمَا": "أُفِعَّتَا",
            "هُنَّ": "أُفْعِلْنَ"
          }
        },
        "2nd": {
          "masculine": {
            "أَنْتَ": "أُفْعِلْتَ",
            "أَنْتُمَا": "أُفْعِلْتُمَا",
            "أَنْتُمْ": "أُفْعِلتُمْ"
          },
          "feminine": {
            "أَنْتِ": "أُفْعِلْتِ",
            "أَنْتُمَا": "أُفْعِلْتُمَا",
            "أَنْتُنَّ": "أُفْعِلتُنَّ"
          }
        },
        "1st": {
          "أَنَا": "أُفْعِلْتُ",
          "نَحْنُ": "أُفْعِلْنَا"
        }
      }
    },
    "مضارع": {
      "معروف": {
        "3rd": {
          "masculine": {
            "هُوَ": "يُفِعُّ",
            "هُمَا": "يُفِعَّانِ",
            "هُمْ": "يُفِعُّوْنَ"
          },
          "feminine": {
            "هِيَ": "تُفِعُّ",
            "هُمَا": "تُفِعَّانِ",
            "هُنَّ": "يُفْعِلْنَ"
          }
        },
        "2nd": {
          "masculine": {
            "أَنْتَ": "تُفِعُّ",
            "أَنْتُمَا": "تُفِعَّانِ",
            "أَنْتُمْ": "تُفِعُّوْنَ"
          },
          "feminine": {
            "أَنْتِ": "تُفِعِّيْنَ",
            "أَنْتُمَا": "تُفِعَّانِ",
            "أَنْتُنَّ": "تُفْعِلْنَ"
          }
        },
        "1st": {
          "أَنَا": "أُفِعُّ",
          "نَحْنُ": "نُفِعُّ"
        }
      },
      "مجهول": {
        "3rd": {
          "masculine": {
            "هُوَ": "يُفَعُّ",
            "هُمَا": "يُفَعَّانِ",
            "هُمْ": "يُفَعُّوْنَ"
          },
          "feminine": {
            "هِيَ": "تُفَعُّ",
            "هُمَا": "تُفَعَّانِ",
            "هُنَّ": "يُفْعَلْنَ"
          }
        },
        "2nd": {
          "masculine": {
            "أَنْتَ": "تُفَعُّ",
            "أَنْتُمَا": "تُفَعَّانِ",
            "أَنْتُمْ": "تُفَعُّوْنَ"
          },
          "feminine": {
            "أَنْتِ": "تُفَعِّيْنَ",
            "أَنْتُمَا": "تُفَعَّانِ",
            "أَنْتُنَّ": "تُفْعَلْنَ"
          }
        },
        "1st": {
          "أَنَا": "أُفَعُّ",
          "نَحْنُ": "نُفَعُّ"
        }
      }
    },
    "نصب": {
      "3rd": {
          "masculine": {
            "هُوَ": "يُفِعَّ",
            "هُمَا": "يُفِعَّا",
            "هُمْ": "يُفِعُّوْا"
          },
          "feminine": {
            "هِيَ": "تُفِعَّ",
            "هُمَا": "تُفِعَّا",
            "هُنَّ": "يُفْعِلْنَ"
          }
        },
        "2nd": {
          "masculine": {
            "أَنْتَ": "تُفِعَّ",
            "أَنْتُمَا": "تُفِعَّا",
            "أَنْتُمْ": "تُفِعُّوْا"
          },
          "feminine": {
            "أَنْتِ": "تُفِعِّيْ",
            "أَنْتُمَا": "تُفِعَّا",
            "أَنْتُنَّ": "تُفْعِلْنَ"
          }
        },
        "1st": {
          "أَنَا": "أُفِعَّ",
          "نَحْنُ": "نُفِعَّ"
        }
      },
    "جزم": {
      "3rd": {
          "masculine": {
            "هُوَ": "يُفِعَّ",
            "هُمَا": "يُفِعَّا",
            "هُمْ": "يُفِعُّوْا"
          },
          "feminine": {
            "هِيَ": "تُفِعَّ",
            "هُمَا": "تُفِعَّا",
            "هُنَّ": "يُفْعِلْنَ"
          }
        },
        "2nd": {
          "masculine": {
            "أَنْتَ": "تُفِعَّ",
            "أَنْتُمَا": "تُفِعَّا",
            "أَنْتُمْ": "تُفِعُّوْا"
          },
          "feminine": {
            "أَنْتِ": "تُفِعِّيْ",
            "أَنْتُمَا": "تُفِعَّا",
            "أَنْتُنَّ": "تُفْعِلْنَ"
          }
        },
        "1st": {
          "أَنَا": "أُفِعَّ",
          "نَحْنُ": "نُفِعَّ"
        }
      },
    "أمر": {
      "2nd": {
        "masculine": {
          "أَنْتَ": "أَفِعَّ",
          "أَنْتُمَا": "أَفِعَّا",
          "أَنْتُمْ": "أَفِعُّوْا"
        },
        "feminine": {
          "أَنْتِ": "أَفِعِّيْ",
          "أَنْتُمَا": "أَفِعَّا",
          "أَنْتُنَّ": "أَفْعِلْنَ"
        }
      }
    }
  }
}
